architecture_checker/__init__.py
architecture_checker/code_analyzer.py
architecture_checker/config_parser.py
architecture_checker/file_regex_collector.py
architecture_checker/main.py
architecture_checker/collectors/__init__.py
architecture_checker/collectors/base_collector.py
architecture_checker/collectors/class_inherits_collector.py
architecture_checker/collectors/collector_factory.py
architecture_checker/collectors/file_regex_collector.py
architecture_checker/rules/__init__.py
architecture_checker/rules/base_rule.py
architecture_checker/rules/dependency_rule.py
architecture_checker/rules/rule_factory.py
tests/__init__.py
tests/test.py
architecture_checker-0.2.9.dist-info/LICENSE
architecture_checker-0.2.9.dist-info/METADATA
architecture_checker-0.2.9.dist-info/WHEEL
architecture_checker-0.2.9.dist-info/entry_points.txt
architecture_checker-0.2.9.dist-info/top_level.txt
architecture_checker-0.2.9.dist-info/RECORD
