Metadata-Version: 2.1
Name: architecture_checker
Version: 0.2.9
Summary: A tool to enforce architectural patterns in python projects
Home-page: https://github.com/vashkatsi/architecture_checker
Author: Archil Abuladze
Author-email: armiworker@gmail.com
Project-URL: Bug Tracker, https://github.com/vashkatsi/architecture_checker/issues
Classifier: Programming Language :: Python :: 3
Classifier: Operating System :: OS Independent
Requires-Python: >=3.6
License-File: LICENSE
Requires-Dist: PyYAML>=5.1
